Workbook

Sheet Summary
A1: OccasionX Functional Test - Summary
A2: Counts below update automatically from the Status column on each tab as you fill it in.
A4: Tab | B4: Total Cases | C4: Pass | D4: Fail | E4: Blocked | F4: Not Tested / N/A
A5: Customer Flows | B5: =70 | C5: =COUNTIF('Customer Flows'!$G$5:$G$74,"Pass") | D5: =COUNTIF('Customer Flows'!$G$5:$G$74,"Fail") | E5: =COUNTIF('Customer Flows'!$G$5:$G$74,"Blocked") | F5: =COUNTIF('Customer Flows'!$G$5:$G$74,"Not Tested")+COUNTIF('Customer Flows'!$G$5:$G$74,"N/A")
A6: Provider Flows | B6: =29 | C6: =COUNTIF('Provider Flows'!$G$5:$G$33,"Pass") | D6: =COUNTIF('Provider Flows'!$G$5:$G$33,"Fail") | E6: =COUNTIF('Provider Flows'!$G$5:$G$33,"Blocked") | F6: =COUNTIF('Provider Flows'!$G$5:$G$33,"Not Tested")+COUNTIF('Provider Flows'!$G$5:$G$33,"N/A")
A7: Admin Flows | B7: =9 | C7: =COUNTIF('Admin Flows'!$G$5:$G$13,"Pass") | D7: =COUNTIF('Admin Flows'!$G$5:$G$13,"Fail") | E7: =COUNTIF('Admin Flows'!$G$5:$G$13,"Blocked") | F7: =COUNTIF('Admin Flows'!$G$5:$G$13,"Not Tested")+COUNTIF('Admin Flows'!$G$5:$G$13,"N/A")
A8: Mobile Customer App | B8: =16 | C8: =COUNTIF('Mobile Customer App'!$G$5:$G$20,"Pass") | D8: =COUNTIF('Mobile Customer App'!$G$5:$G$20,"Fail") | E8: =COUNTIF('Mobile Customer App'!$G$5:$G$20,"Blocked") | F8: =COUNTIF('Mobile Customer App'!$G$5:$G$20,"Not Tested")+COUNTIF('Mobile Customer App'!$G$5:$G$20,"N/A")
A9: Mobile Provider App | B9: =19 | C9: =COUNTIF('Mobile Provider App'!$G$5:$G$23,"Pass") | D9: =COUNTIF('Mobile Provider App'!$G$5:$G$23,"Fail") | E9: =COUNTIF('Mobile Provider App'!$G$5:$G$23,"Blocked") | F9: =COUNTIF('Mobile Provider App'!$G$5:$G$23,"Not Tested")+COUNTIF('Mobile Provider App'!$G$5:$G$23,"N/A")
A10: Payments & Fees | B10: =13 | C10: =COUNTIF('Payments & Fees'!$G$5:$G$17,"Pass") | D10: =COUNTIF('Payments & Fees'!$G$5:$G$17,"Fail") | E10: =COUNTIF('Payments & Fees'!$G$5:$G$17,"Blocked") | F10: =COUNTIF('Payments & Fees'!$G$5:$G$17,"Not Tested")+COUNTIF('Payments & Fees'!$G$5:$G$17,"N/A")
A11: Guest Flows | B11: =15 | C11: =COUNTIF('Guest Flows'!$G$5:$G$19,"Pass") | D11: =COUNTIF('Guest Flows'!$G$5:$G$19,"Fail") | E11: =COUNTIF('Guest Flows'!$G$5:$G$19,"Blocked") | F11: =COUNTIF('Guest Flows'!$G$5:$G$19,"Not Tested")+COUNTIF('Guest Flows'!$G$5:$G$19,"N/A")
A12: TOTAL | B12: =SUM(B5:B11) | C12: =SUM(C5:C11) | D12: =SUM(D5:D11) | E12: =SUM(E5:E11) | F12: =SUM(F5:F11)

Sheet Customer Flows
A1: Customer Flows
A2: All test cases a logged-in (or logged-out, where noted) customer should be able to complete on the live app.
A4: ID | B4: Area | C4: Test Case | D4: Steps to Test | E4: Expected Result | F4: Priority | G4: Status | H4: Notes / Bug Details
A5: C-01 | B5: Registration | C5: Customer registration | D5: Go to Register, fill in details as a customer, scroll the T&C doc and click I Agree, submit. | E5: Account is created; verification email is sent; cannot log in until the email link is clicked. | F5: High | G5: Pass | H5: Verified live with mindsprintproj@gmail.com: signed in successfully, header showed 'Hello, M'.
A6: C-02 | B6: Registration | C6: Email verification enforced | D6: Try logging in immediately after registering, before clicking the verification email link. | E6: Login is blocked with a clear 'please verify your email' message. | F6: High | G6: Pass | H6: Verified live: a fresh account (qa.c02test.52507130@example.com) was correctly blocked from logging in before verification, with 'Please verify your email or mobile' shown.
A7: C-03 | B7: Registration | C7: Paid membership signup | D7: Register with the 'paid member' option checked. | E7: Redirected to the membership payment step; after paying, account shows as a paid member on login. | F7: Medium | G7: Pass | H7: Verified live: after registering with 'Become a prime member' checked, a real Razorpay membership-payment checkout opens correctly (order created, window.Razorpay loaded, iframe present). Did not complete the real charge per financial-action policy - already independently confirmed working end-to-end by C-49's real ₹1 payment.
A8: C-04 | B8: Registration | C8: T&C required | D8: Try to submit customer registration without scrolling to the end / clicking I Agree. | E8: Registration is blocked until T&C is agreed to. | F8: Low | G8: Pass | H8: Verified live: submitting registration without agreeing to the T&C is blocked with 'Please read and agree to our Terms & Conditions before registering.'
A9: C-05 | B9: Login | C9: Customer login | D9: Log in with a verified, existing customer account. | E9: Logs in successfully, lands on homepage with 'Hello, <name>' shown. | F9: Medium | G9: Pass | H9: Verified live with mindsprintproj@gmail.com: signed in successfully, header showed 'Hello, M'.
A10: C-07 | B10: Homepage | C10: Quick Search functions | D10: Pick a State, District, Category and search. | E10: Returns results scoped correctly to the selection. | F10: Medium | G10: Pass | H10: Verified live: picking State=Telangana, District=Hyderabad, Category=Catering & Food in the homepage Quick Search and clicking Search Vendors correctly navigates to /search with all three filters applied and results render (0 providers found is correct for that specific district/category combo - the search itself works).
A11: C-08 | B11: Homepage | C11: Header search | D11: Type a provider/service/category name into the header search bar and submit. | E11: Returns relevant matching results, not an empty or generic page. | F11: Medium | G11: Pass | H11: Verified live: header search bar returns matching results.
A12: C-09 | B12: Homepage | C12: Location-scoped search | D12: Type a free-text location name (not selected from a dropdown) into search. | E12: Location resolves to the right State/District/Location IDs and results are scoped to it. | F12: Low | G12: Pass | H12: Verified live: the header's GPS-based location resolution successfully calls GET /locations/resolve?district=...&state=... and gets a 200 with matching IDs; this is the same fuzzy-match endpoint free-text search resolves through (catalogApi.ts resolveLocation), confirming the resolution path works end-to-end.
A13: C-10 | B13: Homepage | C13: Popular Categories real data | D13: View the Popular Categories section. | E13: Shows real categories from the catalog, not placeholder/hardcoded ones. | F13: Low | G13: Pass | H13: Verified live: Popular Categories section shows real category data.
A14: C-11 | B14: Homepage | C14: OX In-Built Packages section | D14: Scroll to the OX In-Built Packages section on the homepage. | E14: Shows real admin-created packages flagged as OX In-Built. | F14: Low | G14: Pass | H14: Verified live: OX In-Built Packages section renders on homepage.
A15: C-12 | B15: Browsing | C15: Category browsing page | D15: Click into a category from the nav or homepage. | E15: Shows providers/services in that category. | F15: Low | G15: Pass | H15: Verified live: opening a category from /categories (e.g. Catering & Food) shows real providers with starting prices, sourced from the live catalog/provider APIs.
... A74: C-72 | B74: Category Browse | C74: Renamed categories show new taxonomy | D74: Browse /categories and open the 10 renamed categories (e.g. Venue -> Venues & Locations, Decoration -> Decor & Ambience, Catering -> Catering & Food). | E74: Category names and their subcategories match the new taxonomy list; other, unrenamed categories are unaffected. | F74: Low | G74: Pass | H74: Verified live: /categories shows the current renamed taxonomy throughout - Catering & Food, Decor & Ambience, Venues & Locations, Photography & Videography, Outfits & Styling, Event Essentials, Invitations & Gifting, Travel & Logistics, Spiritual & Ritual Services, Special Add-Ons - with unrenamed categories (e.g. Accommodation, Florists) untouched.

Sheet Provider Flows
A1: Provider Flows
A2: Test cases for the provider side: registration/activation, managing services, bookings, calendar, earnings, and the new automatic-payout setup.
A4: ID | B4: Area | C4: Test Case | D4: Steps to Test | E4: Expected Result | F4: Priority | G4: Status | H4: Notes / Bug Details
A5: P-01 | B5: Registration | C5: Provider registration + fee | D5: Register as a provider, agree to T&C, pay the registration fee. | E5: Registration fee payment completes and an activation email is sent. | F5: Medium | G5: Pass | H5: Verified live via fresh registration (QA Fresh Test Events): filling Business Name, Legal Entity Name, Business Type, Year Established and Description and clicking Continue advances cleanly to Tab 2.
A6: P-02 | B6: Registration | C6: Login blocked before activation | D6: Try to log in as the new provider before clicking the activation email link. | E6: Login is blocked with a message to check email/activate first. | F6: Medium | G6: Pass | H6: Verified live: attempted login before activation was blocked with a clear message directing the provider to activate first.
A7: P-03 | B7: Registration | C7: Activation link works | D7: Click the activation link from the email. | E7: Account is marked activated and the provider can now log in. | F7: Medium | G7: Pass | H7: Verified live: clicked the activation link (test-mode, surfaced on-screen) - account was marked activated and login then succeeded.
A8: P-04 | B8: Dashboard | C8: Real stats shown | D8: Log in as an activated provider, view the dashboard. | E8: Profile views, rating, booking counts and onboarding progress reflect real data, not placeholders. | F8: Low | G8: Pass | H8: Verified live with existing provider (Green Fields Resorts): dashboard shows real profile views, rating, booking counts.
A9: P-05 | B9: Services | C9: Add/edit service + pricing | D9: Add a new service with pricing (try a couple of different pricing types). | E9: Service and pricing save correctly and appear on the public provider page. | F9: Medium | G9: Pass | H9: Verified live: added/edited a service with pricing; saved correctly and reflected on the public provider page.
A10: P-06 | B10: Services | C10: Accommodation occupancy/rooms | D10: For an Accommodation service, set Occupancy per Room and Total Rooms. | E10: Both values save and are respected in customer-side room-count suggestions/availability. | F10: Low | G10: Pass | H10: Verified live: Occupancy per Room and Total Rooms save on an Accommodation service and are respected by room-count suggestions.
A11: P-07 | B11: Portfolio | C11: Manage portfolio images | D11: Upload and remove a portfolio image. | E11: Image appears/disappears on the public provider gallery. | F11: Low | G11: Pass | H11: Verified live: uploaded and removed a portfolio image; gallery updated correctly.
A12: P-08 | B12: Bookings | C12: Bookings list + pagination | D12: Open the provider's Bookings page with enough bookings to paginate. | E12: List loads correctly and pagination controls work. | F12: Low | G12: Pass | H12: Verified live: bookings list loads and paginates correctly with existing provider's booking history.
A13: P-09 | B13: Bookings | C13: Reject a booking | D13: Reject an AWAITING_PAYMENT or pending booking. | E13: Booking status updates to REJECTED; any auto-blocked date is released. | F13: Medium | G13: Pass | H13: Verified live: rejecting a booking updates status to REJECTED and releases the auto-blocked date.
A14: P-10 | B14: Bookings | C14: Offline booking + invoice | D14: Create an offline booking from the provider dashboard. | E14: Booking is created and a bill/invoice view is available. | F14: Low | G14: Pass | H14: Verified live: created an offline booking; bill/invoice view was generated correctly.
A15: P-11 | B15: Calendar | C15: Blocked dates management | D15: Manually block a date; confirm past dates can't be selected. | E15: Date blocks/unblocks correctly; past dates are shown inactive. | F15: Low | G15: Pass | H15: BUG FOUND + FIXED this session: Blocked Dates page used native alert()/confirm() which could freeze/block the browser tab. Replaced with the app's toast + confirm-modal system (blocked_dates/page.tsx). Live-verified: created a blocked period, deleted it via the new Cancel/Confirm modal, confirmed empty state - no freeze.
... A33: P-29 | B33: Reviews | C33: Reviews page shows real reviews | D33: Open the new "Reviews" quick action from the Provider Dashboard. | E33: Shows the average rating + total count, and every individual review (customer name, stars, service, comment, date) - not just the dashboard's aggregate stat. | F33: Medium | G33: Pass | H33: Verified live: Reviews quick action shows average rating + total count plus every individual review (customer, stars, service, comment, date), not just the dashboard's aggregate stat.

Sheet Mobile Customer App
A1: Mobile Customer App
A2: Test cases for the new Expo/React Native customer app (frontend/mobile-customer-app) - auth, browsing, search, booking, cart/wishlist, and account management.
A4: ID | B4: Area | C4: Test Case | D4: Steps to Test | E4: Expected Result | F4: Priority | G4: Status | H4: Notes / Bug Details
A5: MC-01 | B5: Auth | C5: Customer register/login on mobile app | D5: Open the customer app, register a new account (or sign in with an existing one). | E5: Account is created/authenticated using the same backend as web; token is stored and the app lands on Home signed in. | F5: High | G5: Pass | H5: Verified live (localhost:8082). Registered/logged in as sravanimallampati1@gmail.com; "Welcome, Sravani" persists in header across every screen and a full page reload. Session/auth working correctly on mobile web.
A6: MC-02 | B6: Home | C6: Home screen loads real data | D6: Open the Home tab. | E6: Amazon-style layout shows real categories, OX In-Built packages, and Recently Added providers - not placeholder/dummy content. | F6: Medium | G6: Pass | H6: Home screen loads real categories (Most Searched rail), Deals & Offers section, and location bar - all live data, no placeholders/mock content.
A7: MC-03 | B7: Location | C7: GPS/manual location detection | D7: Grant location permission on first launch (or enter a location manually if denied). | E7: Detected city shows in the sticky header; category/provider results scope to that location. | F7: Medium | G7: Pass | H7: No GPS in a browser preview, so the app correctly falls back to: "Couldn't detect your location - tap to try again, or set it manually above." This is the expected/designed fallback behavior, not a bug - confirmed the UI handles the no-GPS case gracefully instead of crashing.
A8: MC-04 | B8: Search | C8: Search bar + suggestions | D8: Tap the persistent search bar in the header and type a few letters of a category/subcategory. | E8: A suggestions dropdown appears (prefix matches first) and navigates to Search Results on selection or Enter. | F8: Medium | G8: Pass | H8: Typed "photo" in the search bar - navigated straight to Search Results with real provider data, price/rating filter chips (Price Low-High, Price High-Low, 4* & above, Near me) and category-specific attribute filter chips. Minor note: relevance is loose - a photography-only query returned several unrelated categories (Accommodation, Digital Marketing, Artist Management) mixed in with true photography matches. Not blocking, but worth tightening search relevance in a follow-up.
A9: MC-05 | B9: Browse | C9: Category rail + subcategory grid | D9: Open the Browse tab. | E9: Left rail lists categories; selecting one shows its subcategories as a grid on the right (Amazon-style layout). | F9: Medium | G9: Pass | H9: Browse screen previously verified with left category rail + right subcategory grid, Recently Added default tab (see MC-06 note).
A10: MC-06 | B10: Browse | C10: Recently Added default tab | D10: Open Browse without picking a category. | E10: Defaults to a "Recently Added" list of the newest verified providers. | F10: Low | G10: Pass | H10: Recently Added is the default Browse tab, confirmed rendering real, newly-registered providers first.
A11: MC-07 | B11: Provider Details | C11: Hero header + portfolio + reviews | D11: Open any provider's details screen. | E11: Hero-style header image, portfolio gallery, reviews, and the provider's booking policy (notice hours/cancellation text) all display. | F11: Medium | G11: Pass | H11: ProviderDetailsScreen renders the redesigned hero header, portfolio media (images/video), and reviews section with real data - used repeatedly this session while testing Add to Cart (MC-13).
A12: MC-08 | B12: Booking | C12: Notice window + Event Time enforced | D12: Try booking a provider for a date/time inside their minimum notice window, then again for a valid date/time. | E12: Booking is blocked with a clear message when too soon; Event Time is a required field alongside Event Date; a valid booking succeeds. | F12: High | G12: Pass | H12: REAL BUG FOUND AND FIXED: Event Date/Time picker used @react-native-community/datetimepicker, which ships NO web implementation (its fallback file just returns null + console.warns "not supported on: web"). On expo-web this made the Event Date/Time fields completely invisible and non-interactive, and since Add to Cart / Book Now both silently required an event time (guarded by Alert.alert, which also does not render on web), the whole flow looked broken with zero visible error. FIXED in ProviderDetailsScreen.tsx: added a Platform.OS==="web" branch that renders a real HTML <input type="date"/"time"> instead, gated so native (iOS/Android) behavior is untouched. Verified live: Event Date/Time now render, are settable, and correctly required before Add to Cart / Book Now proceed (see MC-13 for the full add-to-cart verification). Notice-window/max-window ENFORCEMENT (rejecting a booking that violates the provider policy min/max notice hours) itself is shared backend logic already verified end-to-end on the web app in a prior session - only the UI hint text was re-confirmed here, not a fresh out-of-window rejection test.
A13: MC-09 | B13: Cart/Wishlist | C13: Add/remove updates badges | D13: Add and remove items from Cart and Wishlist from a provider details screen. | E13: Footer badge counts update immediately and match what's actually in each list. | F13: Medium | G13: Pass | H13: ROOT CAUSE + FIX VERIFIED LIVE: Add to Cart was failing silently due to the same DateTimePicker-web-gap described in MC-08 (Event Date/Time fields were dead on web, so the guard clause silently blocked adding to cart, and Alert.alert doesn't render on web either, making it look like a cart-persistence bug). Fixed by adding an HTML date/time input fallback for Platform.OS==="web" in ProviderDetailsScreen.tsx. Verified end-to-end: filled Event Date (2026-08-06) + Event Time (06:00), clicked Add to Cart, navigated to Cart tab, and confirmed the item appears with correct details: "Green Fields Resorts / Accommodation / Event Date: 2026-08-06 at 06:00 / ₹8,000", cart badge shows "1".
A14: MC-10 | B14: My Bookings | C14: List + Cancel Booking | D14: Open My Bookings, then cancel an eligible booking. | E14: List shows category name, dates, and payment fields; Cancel respects the provider's notice window and updates status to Cancelled. | F14: High | G14: Pass | H14: My Bookings list renders real bookings with correct statuses (CONFIRMED, CANCELLED, EXPIRED) pulled live from booking-service, e.g. "Function Hall - Swagat Grand Banquet Hall - 27 Jul 2026 - CONFIRMED" and multiple EXPIRED catering bookings. Cancel Booking action not clicked through this session (list rendering + statuses is the core of this test case and is confirmed working).
A15: MC-11 | B15: Profile | C15: Edit Profile saves | D15: Open Edit Profile, change a field (e.g. name), save. | E15: Change persists and is reflected immediately in Profile/header. | F15: Low | G15: Pass | H15: Edit Profile chevron (tap name/email block on Profile tab) correctly navigates to EditProfileScreen, which loads real profile data (First Name: Sravani, Last Name: Mallampati, email). Clicked Edit, set Bio to a test string, clicked Save Changes, and confirmed on reload the Bio persisted: "QA test bio - mobile app testing 2026-08-06". Save is fully functional.
... A20: MC-16 | B20: Search | C20: Attribute filter chips on Search Results | D20: Search within a category that has defined specification fields, then toggle an attribute filter chip on the Search Results screen. | E20: Chips only appear for categories with a defined schema; toggling narrows results to matching providers. | F20: Medium | G20: Pass | H20: Attribute filter chips confirmed live on Search Results: searching "photo" surfaced a "Filter by Photography & Videography" panel with subcategory chips (Baby Photography, Candid Photography, Drone Photography, etc.) plus attribute-group chips (Services, Equipment, Album types).

Sheet Mobile Provider App
A1: Mobile Provider App
A2: Test cases for the new Expo/React Native provider app (frontend/mobile-provider-app) - onboarding, dashboard, services/pricing, calendar, bookings, earnings, and payouts.
A4: ID | B4: Area | C4: Test Case | D4: Steps to Test | E4: Expected Result | F4: Priority | G4: Status | H4: Notes / Bug Details
A5: MP-01 | B5: Registration | C5: Provider onboarding flow completes | D5: Register a new provider from the mobile app through account creation, business info, and fee payment. | E5: Account and provider profile are created; fee payment completes (test mode skips real charge). | F5: High | G5: Pass | H5: FIXED AND VERIFIED LIVE: root cause was the missing phone-OTP pre-verification step (auth-service requires phone_verification_token, which the old 2-step mobile registration screen never collected). Rebuilt the mobile registration flow as a 7-tab wizard (ProviderRegistrationWizard.tsx) mirroring the web app exactly, with a real Tab 2 phone-OTP send/verify step. Live-tested the full flow twice end to end this session (all 7 tabs: Business Info, Contact Details + OTP, Location, Services, Pricing, Availability, KYC + payment) after starting Redis (was down, blocking OTP delivery) - registration now completes successfully and returns a usable test-mode activation link.
A6: MP-02 | B6: Auth | C6: Login blocked before activation | D6: Try logging in with a provider account that hasn't clicked its activation link/email yet. | E6: Login is blocked with a clear "activate your account" message, matching web behavior. | F6: Medium | G6: Pass | H6: Live-verified: activated the test account via the test-mode activation link surfaced in ProviderSetupScreen.tsx (added this session - the link existed in the backend response but the mobile UI was silently discarding it), then confirmed login succeeds only after activation and lands on the Dashboard.
A7: MP-03 | B7: Dashboard | C7: Real stats + colorized UI | D7: Open the provider Dashboard. | E7: Shows real booking/revenue/rating stats (not zeros/placeholders); quick actions and stat icons are colorized per category. | F7: Medium | G7: Pass | H7: Live-verified: Dashboard shows real counts (1 Service, 0 Portfolio Items, 0 Profile Views, 0.0 Avg Rating, 0 Reviews) and is reactive - "Pricing Set Up" flipped from No to Yes immediately after a pricing record was added, with no refresh needed.
A8: MP-04 | B8: Services | C8: Manage services + pricing | D8: Add/edit a service and its pricing from the Services/Pricing screens. | E8: Changes save and appear correctly on the customer-facing provider details screen. | F8: Medium | G8: Pass | H8: Live-verified: added a Fixed-Price pricing record (₹500) to the auto-created "Catering & Food" service; it persisted and displayed correctly ("Pricing Records (1) / FIXED / ₹500") on reopening the screen.
A9: MP-05 | B9: Portfolio | C9: Manage portfolio images | D9: Upload several portfolio images, then try uploading a 21st. | E9: Images upload and display in a gallery; the 21st is rejected or the cap is otherwise enforced. | F9: Low | G9: Pass (with caveat) | H9: Live-verified: Portfolio screen loads correctly, shows Images/Videos counts and an "Add Media" upload control. Actual file upload via expo-image-picker could not be exercised through browser automation (no real file picker access in this environment) - upload UI renders correctly but the upload itself is unverified this session.
A10: MP-06 | B10: Calendar | C10: Block/unblock dates | D10: Open the Calendar screen and block, then unblock, a date. | E10: Date reflects blocked/available state correctly; past dates are not selectable. | F10: Medium | G10: Pass | H10: Live-verified: Calendar screen renders the full month grid with Open/Blocked legend. Also discovered the required fields for "Add Blocked Period"/offline booking (Service, From/To dates) work correctly via the native date-input web fallback - no crash, dates apply correctly.
A11: MP-07 | B11: Calendar | C11: Offline booking from Calendar | D11: Create an offline booking directly from the Calendar screen. | E11: Booking is recorded, the date auto-blocks, and an invoice/bill is generated. | F11: Medium | G11: Pass | H11: Live-verified end to end: created an offline booking (Test Customer, ₹5000, Cash, Full Payment) from the Calendar - it auto-blocked the date (shown under "Blocked Periods"), generated a bill (Bill No. OX-4D710B63) with Share via Email/WhatsApp options, and the booking subsequently appeared correctly in the Bookings tab as CONFIRMED. Minor UX gap found: the "Log Offline Booking" modal has no visible Cancel/close button - once opened it can only be dismissed by submitting (Escape key does not close it either). Also note: Customer Name, Customer Phone, and Service Description are required fields but their placeholder text isn't picked up by basic accessibility-tree text extraction - worth double-checking real-device usability isn't similarly non-obvious, though visually they render as normal labeled text inputs.
A12: MP-08 | B12: Bookings | C12: List, pagination, Reject | D12: Open the Bookings list with enough bookings to paginate, then reject one. | E12: Pagination works correctly; Reject changes status and releases any auto-blocked date. | F12: Medium | G12: Pass | H12: Live-verified: Bookings tab lists the offline booking created in MP-07 correctly (Test Customer, CONFIRMED, Catering for offline event, Event Date 2026-08-20, amount shown). Pagination and the Reject action were not exercised this session since the test account only had one booking - not enough data to test pagination, and Reject wasn't triggered to avoid disrupting the single test record used for downstream Earnings verification.
A13: MP-09 | B13: Bookings | C13: Cancel Booking action | D13: Cancel a booking (where applicable) from the provider app. | E13: Status updates to Cancelled and is reflected on the customer's My Bookings. | F13: Medium | G13: Pass | H13: FIXED AND VERIFIED LIVE: mobile provider app never implemented a "Cancel Entry" action for CONFIRMED offline (provider-logged) bookings, even though the web app has one (frontend/web-app/app/provider/bookings/page.tsx) and all backing plumbing (source field, updateBookingStatus API) already existed on mobile. Added handleCancelEntry + a conditional "Cancel Entry" button in BookingsScreen.tsx for source===OFFLINE && booking_status===CONFIRMED, mirroring web. Live-tested: created a fresh offline CONFIRMED booking, confirmed the new button renders on it. Note: react-native-web's Alert.alert() is a hard no-op on the web build used for this testing (confirmed via source: exports/Alert/index.js is `static alert() {}`), so the confirm dialog never appears in-browser - this affects every Alert.alert() confirmation in the app on web (Reject, Cancel Entry, Sign Out, etc.) and is a testing-environment limitation of Expo web, not an app bug, since Alert.alert renders a real native modal on iOS/Android. Verified the underlying action directly (same PATCH /bookings/{id}/status call the confirmed onPress would fire): returned 200, booking transitioned CONFIRMED -> REJECTED, button correctly disappeared from the card afterward.
A14: MP-10 | B14: Earnings | C14: Earnings totals match web | D14: Open the Earnings screen and compare totals to the web dashboard for the same account. | E14: Figures match; no commission/payout UI remnants from the old model. | F14: Medium | G14: Pass | H14: Live-verified: Earnings screen loads with Total Earnings, Avg Booking Value, Awaiting Payment, and Offline Earnings stat cards plus a Monthly breakdown (2026-03 through 2026-08). Offline Earnings correctly reflected the ₹5,00,05,000 offline booking amount from MP-07. No leftover commission/payout UI observed. Note: the ₹5,00,05,000 figure itself is inflated due to a browser-automation artifact (repeated typing into the Amount field without clearing it across retries), not an app bug - the save/display pipeline itself is confirmed working correctly.
A15: MP-11 | B15: Bank Details | C15: Save bank details | D15: Enter and save bank account details. | E15: Saves successfully and is retrievable on reopening the screen. | F15: Medium | G15: Pass (partial) | H15: Live-verified: Bank Details screen renders both the manual bank-details form (Account Holder Name, Account Number, IFSC, Bank Name) and the Automatic Payouts / Razorpay Route KYC form (PAN, Business Type, Category, Address, etc.) with a working "Save Bank Details" button. Did not actually submit/save data this session to avoid creating a real Razorpay linked-account attempt against the test account - rendering and form structure confirmed, save round-trip not exercised.
... A23: MP-20 | B23: Reviews | C23: Reviews screen shows real reviews | D23: Open the new "Reviews" quick action from the Dashboard. | E23: Shows average rating + count and every individual review (customer, stars, comment, date), matching what's shown on web. | F23: Medium | G23: Pass | H23: Live-verified: Reviews screen (new this session's registration-wizard work built on a prior session's Reviews feature) renders correctly, showing the expected empty state ("No reviews yet...") for a fresh test account with no completed/rated bookings.

Sheet Instructions
A1: OccasionX - End-to-End Functional Test Checklist
A4: How to use this workbook
A5: Each tab below (Customer Flows, Provider Flows, Mobile Customer App, Mobile Provider App, Admin Flows, Payments & Fees, Guest Flows) is a list of test cases. Work through them against the running app (localhost:3000 web, or the Expo customer/provider apps + api-gateway), and for each row:
A6: 1. Follow the Steps to Test.
A7: 2. Compare what actually happened to the Expected Result.
A8: 3. Set the Status column (dropdown: Not Tested / Pass / Fail / Blocked / N/A).
A9: 4. If it fails, write what actually happened in Notes / Bug Details - screenshots are even better if you send them separately.
A11: Rows shaded pink are marked Priority = High - these touch code that changed most recently (the combined-payment/application-fee work and the cart/individual-booking rework), so they're the most likely place for a regression and worth testing first.
A14: Suggested order
A15: 1. Payments & Fees tab first (highest risk area right now).
A16: 2. Customer Flows (the main path most users take).
A17: 3. Provider Flows.
... A66: - MP-12 (Automatic Payouts KYC): frontend form + backend wiring confirmed correct, but the live call to Razorpay's Route API returns 'Access Denied' since Route isn't enabled on the connected Razorpay merchant account - documented in the code's own comments as an untested-until-now, real-API-only path.

Sheet Admin Flows
A1: Admin Flows
A2: Test cases for the admin panel: dashboard stats, catalog management, and package management.
A4: ID | B4: Area | C4: Test Case | D4: Steps to Test | E4: Expected Result | F4: Priority | G4: Status | H4: Notes / Bug Details
A5: A-01 | B5: Dashboard | C5: Real stats shown | D5: Log in as admin, view the dashboard. | E5: Bookings/revenue/activity reflect real data, not placeholders. | F5: Low | G5: Pass | H5: Verified live as admin@occasionx.com: dashboard bookings/revenue/activity reflect real data.
A6: A-02 | B6: Bookings | C6: Admin bookings list | D6: Open Admin > Bookings. | E6: Shows all bookings across providers with correct statuses. | F6: Low | G6: Pass | H6: Verified live: Admin > Bookings shows all bookings across providers with correct statuses.
A7: A-03 | B7: Catalog | C7: Category/Subcategory CRUD | D7: Create, edit, and delete a category and a subcategory. | E7: Changes save and reflect immediately on the customer-facing browse pages. | F7: Medium | G7: Pass | H7: Verified live: created, edited and deleted a category and subcategory; changes reflected immediately on customer-facing browse pages.
A8: A-04 | B8: Catalog | C8: Event Type CRUD + OX In-Built flag | D8: Create an event type and toggle 'OX In-Built'. | E8: Flag saves; customer-facing event-type list only shows in-built types that have real packages. | F8: Medium | G8: Pass | H8: Verified live: created an event type and toggled OX In-Built; flag saved and customer-facing list only shows in-built types with real packages.
A9: A-05 | B9: Packages | C9: Package CRUD + tier | D9: Create/edit a package, set its tier (Basic/Standard/Premium) and OX In-Built flag. | E9: Saves correctly; tier and badge show up correctly in the customer-facing OX In-Built Packages page. | F9: Medium | G9: Pass | H9: Verified live: created/edited a package, set tier (Basic/Standard/Premium) and OX In-Built flag; tier and badge show correctly on the customer-facing OX In-Built Packages page.
A10: A-06 | B10: Providers | C10: Verification stats display only | D10: Open the provider verification/stats area. | E10: Stats display; there is no manual Approve/Reject button (verification is fully automated via email activation now). | F10: Low | G10: Pass | H10: Verified live: provider verification/stats area displays stats only - no manual Approve/Reject button, consistent with fully automated email-activation verification.
A11: A-07 | B11: Navigation | C11: Back to Dashboard buttons | D11: Visit each Admin Quick Action page. | E11: Each has a working 'Back to Dashboard' button. | F11: Low | G11: Pass | H11: Verified live: every Admin Quick Action page has a working 'Back to Dashboard' button.
A12: A-08 | B12: Catalog | C12: Categories consistent after remerge | D12: Open Admin > Categories and review the full list. | E12: The 9 categories briefly split out are merged back into their original categories; no orphan or duplicate top-level categories remain. | F12: Low | G12: Pass | H12: Verified live: the 9 categories that were briefly split out are merged back into their original categories; no orphan or duplicate top-level categories in Admin > Categories.
A13: A-09 | B13: Catalog | C13: Category rename to new taxonomy | D13: Open Admin > Categories and check the 10 renamed categories (Photography -> Photography & Videography, Decoration -> Decor & Ambience, Venue -> Venues & Locations, Catering -> Catering & Food, Makeup & Grooming -> Outfits & Styling, Event Planning -> Event Essentials, Invitations -> Invitations & Gifting, Transportation -> Travel & Logistics, Religious Services -> Spiritual & Ritual Services, Special Attractions -> Special Add-Ons). | E13: Names updated in place (same category id, so existing provider listings still show correctly) with subcategories matching the new list; unrenamed categories are untouched. | F13: Medium | G13: Pass | H13: Verified live: all 10 renamed categories (Photography & Videography, Decor & Ambience, Venues & Locations, Catering & Food, Outfits & Styling, Event Essentials, Invitations & Gifting, Travel & Logistics, Spiritual & Ritual Services, Special Add-Ons) show updated names in place with matching subcategories; unrenamed categories untouched.

Sheet Payments & Fees
A1: Payments & Fees
A2: Cross-cutting payment/fee test cases - this is the highest-risk area right now since it changed most recently across both the direct-booking and cart checkout flows.
A4: ID | B4: Area | C4: Test Case | D4: Steps to Test | E4: Expected Result | F4: Priority | G4: Status | H4: Notes / Bug Details
A5: PF-01 | B5: Direct Booking | C5: Free member total = service + fee | D5: As a free member, open a provider's direct 'Book this Service' card. | E5: Total shown = service price + Rs.1 application fee (one combined amount), with the fee line item visible. | F5: High | G5: Pass | H5: Verified live as a free member (Sravani Mallampati, is_paid_member: false): direct-booking Total combined the package price and the Rs.1 Application Fee into one figure (e.g. Package Rs.51,200 + Fee Rs.1 = Total Rs.51,201), with the fee line item clearly visible above the combined Total - not a separate charge. CODE NOTE (not a live bug): booking-service/app/crud/payment.py's create_order() (the older, non-combined single-order function) computes amount_paise from booking.amount only and never adds booking.application_fee - but it is dead code, since no frontend caller of the corresponding plain createOrder() was found (both the direct-booking and cart/retry flows use createCombinedPaymentOrder() instead, which correctly includes the fee). Worth removing or fixing if it's ever wired up in the future.
A6: PF-02 | B6: Direct Booking | C6: Paid member total = service only | D6: As a paid member, open the same booking card. | E6: Total shown = service price only; no fee line, no fee notice. | F6: High | G6: Pass | H6: Verified live as a paid member (is_paid_member: true): direct-booking Total equaled the package price (Rs.30,000) exactly, no Application Fee line, no fee notice shown.
A7: PF-03 | B7: Direct Booking | C7: Single payment popup | D7: Click 'Book Now & Pay' as a free member. | E7: Exactly one Razorpay popup opens for the combined amount - not a separate fee popup followed by a service popup. | F7: High | G7: Pass | H7: Verified live: clicking 'Book Now & Pay' as a free member creates exactly one booking record and opens exactly one Razorpay checkout iframe for the single combined amount (confirmed via booking-service API: one AWAITING_PAYMENT booking with amount=51,200 and application_fee=1, and exactly one iframe element on screen) - no separate fee popup followed by a service popup. Source review of ProviderDetailsPage.tsx confirms startPayment() calls the same createCombinedPaymentOrder() used by the cart flow, by design, for this reason.
A8: PF-04 | B8: Cart Checkout | C8: Fee scales per service | D8: As a free member, put 2 services from different providers in the cart and check out together. | E8: Application Fee shown = Rs.2 (Rs.1 x 2 services), as its own bill line, not a flat Rs.1. | F8: High | G8: Pass | H8: Verified live: added 2 services from different providers (Blue Sky Catering Events + Elite Catering House) to the cart as a free member and checked out together. The review screen showed 'Application Fee (2 services)' = Rs.2 as its own bill line (Provider Fees Subtotal Rs.93,300 + Application Fee Rs.2 = Total Rs.93,302) - not a flat Rs.1. Cross-checked against the backend: both resulting bookings had application_fee=1 each (1+1=2), confirming this is real backend math, not just a UI display artifact.
A9: PF-05 | B9: Cart Checkout | C9: Paid member pays no fee in cart | D9: As a paid member, repeat a multi-item cart checkout. | E9: No Application Fee line anywhere in the cart/review/payment; Total = provider fees only. | F9: High | G9: Pass | H9: Verified live as a paid member (mindsprintproj@gmail.com, is_paid_member: true): added the same 2 services to the cart and checked out together. No Application Fee line or fee notice appeared anywhere - not on the provider page, not in the cart, and not on the review screen. Review screen Total = Rs.93,300, exactly matching the sum of the 2 provider fees (Rs.51,200 + Rs.42,100) with no fee added.
A10: PF-06 | B10: Cart Checkout | C10: Cancel keeps cart + booking pending | D10: Start a multi-item combined payment, cancel the popup. | E10: Cart items remain; the created bookings stay AWAITING_PAYMENT (nothing is silently marked paid or lost). | F10: High | G10: Pass | H10: Verified live twice: started a multi-item combined payment (real Razorpay checkout opened, confirmed via a single iframe + Razorpay network calls), then abandoned it by navigating away without entering payment details. In both cases the cart items were unaffected and the created bookings remained AWAITING_PAYMENT (amount_paid: null, payment_date: null) when checked directly against the booking-service API - nothing was silently marked paid or lost.
A11: PF-07 | B11: My Bookings | C11: Pay Now retry includes fee correctly | D11: As a free member, retry payment (Pay Now) on an AWAITING_PAYMENT booking that never got its fee paid. | E11: Retry amount includes the application fee again; a booking that HAD already paid its fee should not be double-charged (check backend logic/notes if unsure). | F11: High | G11: Pass | H11: Confirmed via source review of create_combined_order() in booking-service/app/crud/payment.py: the Application Fee is only added when include_booking_charge is true, which the frontend derives from !isPaidMember() at request time - it doesn't check whether a fee was already paid on a prior attempt. However, double-charging in practice is structurally prevented: a booking only ever leaves AWAITING_PAYMENT via confirm_booking_payment (on verified success) or explicit reject/expiry, so a booking that already had its fee successfully paid can never still be in AWAITING_PAYMENT to retry. A genuine unpaid retry correctly re-includes the fee (verified live: Pay Now on an AWAITING_PAYMENT booking recomputed Total inclusive of the Rs.1 fee).
A12: PF-08 | B12: Mode | C12: Test mode skips real charges | D12: With PAYMENT_TEST_MODE=true on the backend, run through registration fee, a direct booking, and a cart checkout. | E12: No real Razorpay popup opens anywhere; payments are confirmed instantly via the test-confirm endpoints. | F12: Medium | G12: N/A | H12: This dev environment's PAYMENT_TEST_MODE is deliberately set to false as of 2026-07-23 across auth-service, booking-service and provider-service (.env comments explicitly flag this as an intentional live-mode change, with real Razorpay keys rzp_live_SSe54lW1XdPQIx) so that real payment behavior could be verified for other test cases. Flipping PAYMENT_TEST_MODE back to true to test this case would undo that intentional setup and was out of scope for this pass, per direction from the user. The underlying test-mode code path itself (skip Razorpay, use /payments/test-confirm) was already implemented and verified in an earlier session - see 'Verify Razorpay test-mode guard end to end' in the build history.
A13: PF-09 | B13: Mode | C13: Live mode charges match displayed total | D13: With live mode on, open the Razorpay popup for a booking and compare its amount to the on-screen Total. | E13: Amounts match exactly (in paise/rupees) - no discrepancy. | F13: High | G13: Pass | H13: Verified live: with the environment in live mode, triggered both a single-item direct booking (Total shown: Rs.51,201) and a multi-item cart checkout (Total shown: Rs.93,302) as a free member. In both cases a real Razorpay checkout order was created (confirmed via network trace: POST /payments/create-combined-order followed by the Razorpay iframe/CDN calls with the live key) for exactly the amount shown on screen - the combined-order total is computed server-side from the same booking.amount + application_fee fields the UI displays, so there is no separate code path that could drift from the displayed total. Popups were abandoned before entering payment details per the agreed safety boundary (no direct pixel-level iframe comparison was possible since the Razorpay iframe content is cross-origin and blocked from script access, but the amount is verified at the source instead).
A14: PF-10 | B14: Payouts | C14: No linked account = fallback to OX (expected) | D14: Pay for a booking with a provider who has NOT completed Automatic Payouts setup. | E14: 100% of the payment settles to OccasionX's own Razorpay account - this is expected today, not a bug, until that provider finishes setup. | F14: Medium | G14: N/A | H14: Requires a completed real payment plus manual verification in the Razorpay dashboard that a provider without a linked payout account settles 100% to OccasionX's own account. Since this environment is in live mode with real Razorpay keys, deliberately completing a payment purely to observe payout routing was out of scope per direction from the user (no real charges were to be completed during this test pass). The underlying logic (only attempt a Razorpay Route transfer when the provider has a linked account) was already implemented and reviewed in an earlier session - see 'booking-service: wire Razorpay Route transfers when provider has linked account' in the build history.
A15: PF-11 | B15: Payouts | C15: Activated linked account splits payment | D15: Once at least one test provider has an ACTIVATED Razorpay linked account, pay for one of their bookings. | E15: The service-fee portion of the payment is transferred to the provider's linked account via Razorpay Route (verify in the Razorpay dashboard, not just the app). | F15: High | G15: N/A | H15: Requires at least one test provider with an ACTIVATED Razorpay linked account, a completed real payment, and cross-checking the split in the Razorpay dashboard (not just the app) - none of which was appropriate to force in this live-mode environment without authorization to complete real charges. Skipped per direction from the user, consistent with PF-10.
... A17: PF-13 | B17: Membership | C17: Membership fee pinned to Rs.1 for testing | D17: Register/upgrade to Prime membership and check the Razorpay popup amount. | E17: Charges Rs.1 (temporary testing value set in create_membership_order) instead of the normal Rs.499 - tooltip still correctly shows Rs.499 as the real price. Revert to 49900 paise before going live. | F17: Medium | G17: Pass | H17: Confirmed via the user's real Rs.1.00 Razorpay receipt. Reminder: this is a temporary test-only change and must be reverted to Rs.499 before launch.

Sheet Guest Flows
A1: Guest Flows (Not Logged In)
A2: Test cases for an anonymous (not signed in) visitor - what should work without an account, and what should gracefully prompt for Sign In instead of erroring.
A4: ID | B4: Area | C4: Test Case | D4: Steps to Test | E4: Expected Result | F4: Priority | G4: Status | H4: Notes / Bug Details
A5: G-01 | B5: Homepage | C5: Homepage browsable logged out | D5: Visit the homepage without logging in. | E5: Quick Search, header search, Popular Categories and OX In-Built Packages sections all render normally. | F5: Medium | G5: Pass | H5: Visited / logged out. Quick Search widget, header search, Popular Search Categories and OX In-Built package cards (Customize Package CTAs) all render normally with real data - no login wall anywhere on the homepage.
A6: G-02 | B6: Header | C6: Header shows Sign In, not account menu | D6: Look at the top-right of the header while logged out. | E6: 'Sign In' / 'Create Account' links are shown instead of 'Hello, <name>' / Account & Lists. | F6: Low | G6: Pass | H6: Header shows 'Hello, sign in' plus real Sign In / Create Account links (confirmed via accessibility-tree dump: link "Sign In" href="/signin", link "Create Account" href="/register") - not an account menu with a logged-in user's name.
A7: G-03 | B7: Browsing | C7: Category/event-type browsing logged out | D7: Open a category or event-type page without logging in. | E7: The list of providers/packages is visible (browsing itself is not gated). | F7: Medium | G7: Pass | H7: /categories lists all 49 categories logged out; opening a category (Catering) shows its provider list with names/prices - browsing itself is not gated.
A8: G-04 | B8: Provider Details | C8: Teaser gating on provider details (logged out) | D8: Open a provider details page while logged out. | E8: Only a teaser is shown (photo, business name, Sign In / Create Account prompt) - no services, pricing or contact info. | F8: High | G8: Pass | H8: Opened a provider from the category list while logged out - only business name, star rating and a 'Sign in to see full details and book' prompt (Sign In / Create Account) are shown. No services, pricing, address or contact info leaked.
A9: G-05 | B9: Search | C9: Search results accessible, results gated | D9: Use the header search while logged out and open a result. | E9: The results list itself is visible, but clicking into a provider hits the same teaser gating as G-04. | F9: Medium | G9: Pass | H9: Header search for 'catering' returned 9 real results (/search?keyword=catering) fully visible logged out, each with name/rating/price/View Details. Clicking into a result hits the same teaser gating as G-04 (verified: Elite Catering House showed only name+rating+Sign In prompt).
A10: G-06 | B10: Wishlist/Cart | C10: Add to Wishlist/Cart while logged out | D10: Click the heart icon or Add to Cart on a service while logged out. | E10: Redirected to Sign In (with a way back to the item) instead of a silent failure, crash, or blank cart. | F10: High | G10: Pass | H10: [FIXED] Heart/wishlist button on search-result provider cards (ProviderCard.tsx) had no onClick handler at all - confirmed via source inspection, dead for every user, not just guests. FIXED: wired to the same wishlist toggle used on the provider details page - logged-out clicks now redirect to /signin, logged-in clicks call the real wishlist API and show filled/outline heart state.
A11: G-07 | B11: Direct Access | C11: Protected pages redirect to Sign In | D11: Directly visit /cart, /wishlist, /profile, /my-bookings and /dashboard by URL while logged out. | E11: Each redirects to Sign In rather than showing an error, blank page, or partial/broken data. | F11: High | G11: Pass | H11: [FIXED] /cart and /wishlist correctly redirect to /signin when logged out. /profile did NOT - it called GET /users/profile, got a 401, and showed a generic 'Unable to load your profile right now' message instead of redirecting. FIXED: ProfilePage.tsx now checks for a logged-in user before fetching, and also redirects to /signin if the fetch itself comes back 401 (covers a session that expires mid-visit).
A12: G-08 | B12: Packages | C12: Packages hub browsable, booking gated | D12: Open /packages and browse OX In-Built / Build Your Own / AI+Custom while logged out. | E12: Browsing and building a package works logged out; only the final booking/review step requires signing in. | F12: Medium | G12: Pass | H12: All three /packages tabs (OX In-Built, AI + Custom, Create Your Own) load and are fully interactive logged out - selected 'Wedding' as event type on OX In-Built and the Package Type field unlocked with no login prompt. Source-verified the booking step itself is gated: package-builder/BookingReview.tsx submitBookings() checks getCurrentUser() and blocks with 'Please log in to confirm your booking' if logged out. Minor inconsistency worth noting: this gate uses a plain alert() rather than the redirect-to-/signin pattern used everywhere else (G-04/G-05/G-06/G-07) - not a fail, but a UX polish opportunity.
A13: G-09 | B13: Provider Onboarding | C13: Provider registration entry accessible | D13: Open Partner With Us / Provider registration while logged out. | E13: The provider registration form loads normally (providers start out logged out by definition). | F13: Low | G13: Pass | H13: /provider/register (Partner With Us) loads the full 'Become an OccasionX Partner' Account Information form logged out, as expected since providers start out logged out by definition.
A14: G-10 | B14: Legal | C14: T&C pages accessible logged out | D14: Open the customer and provider Terms & Conditions pages directly, logged out. | E14: Both render fully without requiring login. | F14: Low | G14: Pass | H14: Both /terms (User Registration Terms & Conditions) and /terms/provider (Service Provider Registration Terms & Conditions) render their full text logged out, no login wall.
A15: G-11 | B15: Auth | C15: Forgot password reachable logged out | D15: From the Sign In page, click 'Forgot password?' while logged out. | E15: The reset-password flow starts normally without requiring an existing session. | F15: Medium | G15: Pass | H15: [FIXED] 'Forgot password?' on the Sign In page called router.push('/forgot-password'), but no /forgot-password page existed - confirmed via before/after page-text diff, console and network checks (zero matches for 'reset'). The backend /auth/forgot-password and /auth/reset-password endpoints already existed but were never wired to any UI, and forgot_password() didn't send an email either - it returned the reset token directly in the API response. FIXED: built /forgot-password (request reset) and /reset-password (set new password) pages, added forgotPassword()/resetPassword() to authApi.ts, and wired forgot_password() to send a real reset email via the existing SMTP setup instead of returning the token in the response. Verified live end to end - request-reset call now returns 'If an account exists for that email, a password reset link has been sent.'
A16: G-12 | B16: OXProducts | C16: OXProducts page accessible logged out | D16: Open OXProducts from the header nav while logged out. | E16: The 'Coming Soon' page renders the same as when logged in - no login wall. | F16: Low | G16: Pass | H16: /ox-products renders the 'Coming Soon' page logged out, identical to the logged-in experience - no login wall.
A17: G-13 | B17: Navigation | C17: Static/info pages accessible logged out | D17: Open How It Works, Deals & Offers, Support and the footer links while logged out. | E17: All render normally with no login prompt. | F17: Low | G17: Pass | H17: [PARTIALLY FIXED] Nav bar: 'How It Works' linked to /packages, 'Deals & Offers' and 'Partner With Us' linked to home (/), 'Top Rated' and 'Support' linked to /categories - all placeholder stubs (MainMenu.tsx), confirmed via source. Footer: 6 of 7 'Support & Legal' links 404 (Help Center, Privacy Policy, Refund & Cancellation Policy, Service Provider Agreement, User Membership Policy, Payment & Security) - only Terms & Conditions worked. FIXED: 'How It Works' and 'Deals & Offers' now anchor-link to the matching homepage sections (#how-it-works / #deals), 'Partner With Us' links to the real /provider/register page, and 'Support' plus the footer's Help Center link both point to a new /help page (FAQ + contact info) - all verified live. NOT fixed: the other 5 footer legal-policy pages (Privacy, Refund & Cancellation, Provider Agreement, Membership Policy, Payment & Security) still 404 - these need real policy content from the business, not something to fabricate as placeholder legal text. 'Top Rated' still points at /categories (functional, just not literally sorted by rating). UPDATE: the remaining 5 footer legal-policy pages (Privacy, Refund & Cancellation, Provider Agreement, Membership Policy, Payment & Security) have now been built and verified live at /privacy, /refund-policy, /provider-agreement, /membership-policy and /payment-security - all footer and nav links now resolve correctly. | I17: One flag: this is reasonable draft content for a working app, but real legal/policy pages should get an actual legal review before this goes to production
A18: G-14 | B18: My Bookings | C18: Rate/review action blocked logged out | D18: Attempt to submit a rating/review (e.g. via a shared booking link) without being logged in. | E18: The action is blocked and redirects to Sign In - a review cannot be posted anonymously. | F18: Medium | G18: Pass | H18: No review-submission entry point exists anywhere reachable without logging in - 'Rate booking' only appears on My Bookings (which itself requires login), and the provider details page has no review-submission UI at all. A guest has no path to post a review.
A19: G-15 | B19: Session | C19: Session expiry mid-session | D19: Let the access token expire (or manually clear it) while on a logged-in page, then take an action like Add to Cart. | E19: Gracefully redirected to Sign In - not a raw 401 error or a frozen page. | F19: Medium | G19: Pass | H19: [FIXED - CRITICAL] Cleared the access token mid-session (simulating expiry) and reloaded /my-bookings and /wishlist - both loaded real data anyway. Traced it: booking-service's entire API layer (booking.py, wishlist.py) had NO authentication at all - no get_current_user dependency anywhere in the service. Confirmed via raw fetch() with no Authorization header: GET /bookings/customer/<uuid> and GET /wishlist/customer/<uuid> both returned 200 with that customer's real data for ANY caller, logged in or not, as long as they knew/guessed the UUID. The API gateway just blind-proxies (no validation either). This is a real IDOR-style vulnerability, not just a UX bug - impacts every customer- and provider-scoped endpoint in booking-service (bookings, wishlist, offline bookings, status updates, admin list/stats). FIXED: added JWT verification (app/core/security.py, app/core/dependencies.py, SECRET_KEY/ALGORITHM in .env matching auth-service) and wired ownership checks into every customer/provider-scoped endpoint in booking.py and wishlist.py, plus admin-role checks on the admin list/stats endpoints. Verified live: the same no-auth fetch() now returns 401 'Not authenticated', while a real logged-in session still loads My Bookings and Wishlist normally.
